{
  "books": [
    {
      "id": 2,
      "name": "You don't know JavaScript",
      "pic": "http://covers.openlibrary.org/b/isbn/0879101342-M.jpg",
      "author": "Kyle Simpsons",
      "sold": false,
      "ISBN": "0879101342"
    },
    {
      "id": 1,
      "name": "You don't know JavaScript",
      "pic": "http://covers.openlibrary.org/b/isbn/0582080533-M.jpg",
      "author": "Kyle Simpsons",
      "sold": true,
      "ISBN": "0582080533"
    },
    {
      "id": "b8ae9eac-e72d-4668-a10e-574e42424324",
      "name": "Weekly Newsletter",
      "author": "Joseph Khan",
      "pic": "http://covers.openlibrary.org/b/isbn/0879101342-M.jpg",
      "sold": false,
      "ISBN": "087910134xx"
    },
    {
      "id": "2442619f-6688-4e09-9f25-9ff26c4cfd3c",
      "name": "JavaScript",
      "author": "Joseph Khan",
      "pic": "http://covers.openlibrary.org/b/isbn/0879101342-M.jpg",
      "sold": false,
      "ISBN": "087910134xx"
    }
  ]
}